odoo/addons/helpdesk_type/README.rst
odoo/addons/helpdesk_type/__init__.py
odoo/addons/helpdesk_type/__manifest__.py
odoo/addons/helpdesk_type/demo/helpdesk_type_demo.xml
odoo/addons/helpdesk_type/i18n/es.po
odoo/addons/helpdesk_type/i18n/es_AR.po
odoo/addons/helpdesk_type/i18n/helpdesk_type.pot
odoo/addons/helpdesk_type/i18n/pt_BR.po
odoo/addons/helpdesk_type/models/__init__.py
odoo/addons/helpdesk_type/models/helpdesk_ticket.py
odoo/addons/helpdesk_type/models/helpdesk_ticket_team.py
odoo/addons/helpdesk_type/models/helpdesk_ticket_type.py
odoo/addons/helpdesk_type/readme/CONFIGURE.rst
odoo/addons/helpdesk_type/readme/CONTRIBUTORS.rst
odoo/addons/helpdesk_type/readme/DESCRIPTION.rst
odoo/addons/helpdesk_type/readme/USAGE.rst
odoo/addons/helpdesk_type/security/ir.model.access.csv
odoo/addons/helpdesk_type/static/description/icon.png
odoo/addons/helpdesk_type/static/description/index.html
odoo/addons/helpdesk_type/views/helpdesk_ticket.xml
odoo/addons/helpdesk_type/views/helpdesk_ticket_team.xml
odoo/addons/helpdesk_type/views/helpdesk_ticket_type.xml
odoo13_addon_helpdesk_type-13.0.1.1.0.dist-info/METADATA
odoo13_addon_helpdesk_type-13.0.1.1.0.dist-info/WHEEL
odoo13_addon_helpdesk_type-13.0.1.1.0.dist-info/top_level.txt
odoo13_addon_helpdesk_type-13.0.1.1.0.dist-info/RECORD
